jvi/__init__.py
jvi/bin/jvi-blur-x.py
jvi/bin/jvi-blur.py
jvi/bin/jvi-box.py
jvi/bin/jvi-cut.py
jvi/bin/jvi-ff-remux.py
jvi/bin/jvi-ff-split.py
jvi/bin/jvi-img2video.py
jvi/bin/jvi-imp.py
jvi/bin/jvi-infrared.py
jvi/bin/jvi-letterbox.py
jvi/bin/jvi-resize.py
jvi/bin/jvi-superres.py
jvi/bin/jvi-tile-dir.py
jvi/bin/jvi-tile-match.py
jvi/bin/jvi-tile-viewer.py
jvi/bin/jvi-tks.py
jvi/bin/jvi-video2img.py
jvi/common.py
jvi/drawing/__init__.py
jvi/drawing/color.py
jvi/drawing/shape.py
jvi/geo/__init__.py
jvi/geo/convert.py
jvi/geo/gp.py
jvi/geo/line_segment.py
jvi/geo/point2d.py
jvi/geo/polygon.py
jvi/geo/protocol.py
jvi/geo/rectangle.py
jvi/geo/size2d.py
jvi/geo/trans.py
jvi/gui/__init__.py
jvi/gui/image_viewer.py
jvi/gui/image_win.py
jvi/gui/imp_win.py
jvi/gui/record_viewer.py
jvi/gui/video_viewer.py
jvi/image/__init__.py
jvi/image/image.py
jvi/image/image_factory.py
jvi/image/image_nda.py
jvi/image/infrared.py
jvi/image/io.py
jvi/image/proc.py
jvi/image/sc3c.py
jvi/image/stat.py
jvi/image/struct.py
jvi/image/tile.py
jvi/image/tile_set.py
jvi/image/trace.py
jvi/image/trans.py
jvi/image/util.py
jvi/match/__init__.py
jvi/match/match.py
jvi/match/match_template.py
jvi/py.typed
jvi-0.3.13.dist-info/METADATA
jvi-0.3.13.dist-info/WHEEL
jvi-0.3.13.dist-info/RECORD
